[
  {
    "Id": "in_strong_vaultdoor00",
    "Translation": [
      37825.332,
      -21487.26,
      1438.0
    ],
    "Rotation": [
      0.0,
      0.0,
      0.74159265
    ],
    "Owner": null,
    "Faction": null,
    "FactionRank": 0,
    "OwnerGlobal": null,
    "Health": 0,
    "Count": 0,
    "Lock": 0,
    "Trap": null,
    "Key": null,
    "Soul": null,
    "Charge": 0,
    "Blocked": 0
  },
  {
    "Id": "in_strong_vaultdoor00",
    "Translation": [
      35805.87,
      -22097.42,
      2110.0
    ],
    "Rotation": [
      0.0,
      0.0,
      2.3123887
    ],
    "Owner": null,
    "Faction": null,
    "FactionRank": 0,
    "OwnerGlobal": null,
    "Health": 0,
    "Count": 0,
    "Lock": 0,
    "Trap": null,
    "Key": null,
    "Soul": null,
    "Charge": 0,
    "Blocked": 0
  },
  {
    "Id": "in_strong_vaultdoor00",
    "Translation": [
      34639.598,
      -20243.893,
      2142.0
    ],
    "Rotation": [
      0.0,
      0.0,
      2.3123887
    ],
    "Owner": null,
    "Faction": null,
    "FactionRank": 0,
    "OwnerGlobal": null,
    "Health": 0,
    "Count": 0,
    "Lock": 0,
    "Trap": null,
    "Key": null,
    "Soul": null,
    "Charge": 0,
    "Blocked": 0
  },
  {
    "Id": "in_strong_vaultdoor00",
    "Translation": [
      35773.977,
      -20853.12,
      1438.0
    ],
    "Rotation": [
      0.0,
      0.0,
      2.3123887
    ],
    "Owner": null,
    "Faction": null,
    "FactionRank": 0,
    "OwnerGlobal": null,
    "Health": 0,
    "Count": 0,
    "Lock": 0,
    "Trap": null,
    "Key": null,
    "Soul": null,
    "Charge": 0,
    "Blocked": 0
  },
  {
    "Id": "virvyn athren",
    "Translation": [
      34975.223,
      -21514.838,
      2054.0938
    ],
    "Rotation": [
      0.0,
      0.0,
      3.483185
    ],
    "Owner": null,
    "Faction": null,
    "FactionRank": 0,
    "OwnerGlobal": null,
    "Health": 0,
    "Count": 0,
    "Lock": 0,
    "Trap": null,
    "Key": null,
    "Soul": null,
    "Charge": 0,
    "Blocked": 0
  },
  {
    "Id": "dathus selvilo",
    "Translation": [
      34654.07,
      -19783.076,
      2065.2793
    ],
    "Rotation": [
      0.0,
      0.0,
      3.083184
    ],
    "Owner": null,
    "Faction": null,
    "FactionRank": 0,
    "OwnerGlobal": null,
    "Health": 0,
    "Count": 0,
    "Lock": 0,
    "Trap": null,
    "Key": null,
    "Soul": null,
    "Charge": 0,
    "Blocked": 0
  },
  {
    "Id": "tanel faren",
    "Translation": [
      34645.285,
      -19452.494,
      2060.927
    ],
    "Rotation": [
      0.0,
      0.0,
      2.7831855
    ],
    "Owner": null,
    "Faction": null,
    "FactionRank": 0,
    "OwnerGlobal": null,
    "Health": 0,
    "Count": 0,
    "Lock": 0,
    "Trap": null,
    "Key": null,
    "Soul": null,
    "Charge": 0,
    "Blocked": 0
  },
  {
    "Id": "tevyn athin",
    "Translation": [
      36072.453,
      -20823.248,
      1382.949
    ],
    "Rotation": [
      0.0,
      0.0,
      0.583187
    ],
    "Owner": null,
    "Faction": null,
    "FactionRank": 0,
    "OwnerGlobal": null,
    "Health": 0,
    "Count": 0,
    "Lock": 0,
    "Trap": null,
    "Key": null,
    "Soul": null,
    "Charge": 0,
    "Blocked": 0
  },
  {
    "Id": "ex_stronghold_sandpit00",
    "Translation": [
      35077.0,
      -19646.451,
      2048.0
    ],
    "Rotation": [
      0.0,
      0.0,
      3.8831854
    ],
    "Owner": null,
    "Faction": null,
    "FactionRank": 0,
    "OwnerGlobal": null,
    "Health": 0,
    "Count": 0,
    "Lock": 0,
    "Trap": null,
    "Key": null,
    "Soul": null,
    "Charge": 0,
    "Blocked": 0
  },
  {
    "Id": "ex_stronghold_fort02",
    "Translation": [
      35155.824,
      -19490.822,
      1758.0
    ],
    "Rotation": [
      0.0,
      0.0,
      3.8831854
    ],
    "Owner": null,
    "Faction": null,
    "FactionRank": 0,
    "OwnerGlobal": null,
    "Health": 0,
    "Count": 0,
    "Lock": 0,
    "Trap": null,
    "Key": null,
    "Soul": null,
    "Charge": 0,
    "Blocked": 0
  },
  {
    "Id": "ex_stronghold_fort03",
    "Translation": [
      38405.94,
      -22105.896,
      1884.0
    ],
    "Rotation": [
      0.0,
      0.0,
      0.74159265
    ],
    "Owner": null,
    "Faction": null,
    "FactionRank": 0,
    "OwnerGlobal": null,
    "Health": 0,
    "Count": 0,
    "Lock": 0,
    "Trap": null,
    "Key": null,
    "Soul": null,
    "Charge": 0,
    "Blocked": 0
  },
  {
    "Id": "ex_stronghold_wall02",
    "Translation": [
      37099.824,
      -19694.389,
      1442.0
    ],
    "Rotation": [
      0.0,
      0.0,
      2.3123891
    ],
    "Owner": null,
    "Faction": null,
    "FactionRank": 0,
    "OwnerGlobal": null,
    "Health": 0,
    "Count": 0,
    "Lock": 0,
    "Trap": null,
    "Key": null,
    "Soul": null,
    "Charge": 0,
    "Blocked": 0
  },
  {
    "Id": "ex_stronghold_wall00",
    "Translation": [
      36958.258,
      -19564.701,
      1442.0
    ],
    "Rotation": [
      0.0,
      0.0,
      5.4539824
    ],
    "Owner": null,
    "Faction": null,
    "FactionRank": 0,
    "OwnerGlobal": null,
    "Health": 0,
    "Count": 0,
    "Lock": 0,
    "Trap": null,
    "Key": null,
    "Soul": null,
    "Charge": 0,
    "Blocked": 0
  },
  {
    "Id": "ex_stronghold_wall02",
    "Translation": [
      37768.652,
      -20307.037,
      1440.0
    ],
    "Rotation": [
      0.0,
      0.0,
      5.4539824
    ],
    "Owner": null,
    "Faction": null,
    "FactionRank": 0,
    "OwnerGlobal": null,
    "Health": 0,
    "Count": 0,
    "Lock": 0,
    "Trap": null,
    "Key": null,
    "Soul": null,
    "Charge": 0,
    "Blocked": 0
  },
  {
    "Id": "ex_stronghold_wall00",
    "Translation": [
      37910.234,
      -20436.729,
      1440.0
    ],
    "Rotation": [
      0.0,
      0.0,
      2.3123891
    ],
    "Owner": null,
    "Faction": null,
    "FactionRank": 0,
    "OwnerGlobal": null,
    "Health": 0,
    "Count": 0,
    "Lock": 0,
    "Trap": null,
    "Key": null,
    "Soul": null,
    "Charge": 0,
    "Blocked": 0
  },
  {
    "Id": "ex_stronghold_wall00",
    "Translation": [
      38099.004,
      -20609.639,
      1440.0
    ],
    "Rotation": [
      0.0,
      0.0,
      2.3123891
    ],
    "Owner": null,
    "Faction": null,
    "FactionRank": 0,
    "OwnerGlobal": null,
    "Health": 0,
    "Count": 0,
    "Lock": 0,
    "Trap": null,
    "Key": null,
    "Soul": null,
    "Charge": 0,
    "Blocked": 0
  },
  {
    "Id": "ex_stronghold_wall00",
    "Translation": [
      38287.77,
      -20782.564,
      1440.0
    ],
    "Rotation": [
      0.0,
      0.0,
      2.3123891
    ],
    "Owner": null,
    "Faction": null,
    "FactionRank": 0,
    "OwnerGlobal": null,
    "Health": 0,
    "Count": 0,
    "Lock": 0,
    "Trap": null,
    "Key": null,
    "Soul": null,
    "Charge": 0,
    "Blocked": 0
  },
  {
    "Id": "ex_stronghold_wall00",
    "Translation": [
      38470.645,
      -20950.076,
      1440.0
    ],
    "Rotation": [
      0.0,
      0.0,
      2.3123891
    ],
    "Owner": null,
    "Faction": null,
    "FactionRank": 0,
    "OwnerGlobal": null,
    "Health": 0,
    "Count": 0,
    "Lock": 0,
    "Trap": null,
    "Key": null,
    "Soul": null,
    "Charge": 0,
    "Blocked": 0
  },
  {
    "Id": "ex_stronghold_wall00",
    "Translation": [
      38659.418,
      -21122.998,
      1440.0
    ],
    "Rotation": [
      0.0,
      0.0,
      2.3123891
    ],
    "Owner": null,
    "Faction": null,
    "FactionRank": 0,
    "OwnerGlobal": null,
    "Health": 0,
    "Count": 0,
    "Lock": 0,
    "Trap": null,
    "Key": null,
    "Soul": null,
    "Charge": 0,
    "Blocked": 0
  },
  {
    "Id": "ex_stronghold_wall01",
    "Translation": [
      38851.168,
      -21363.736,
      1440.0
    ],
    "Rotation": [
      0.0,
      0.0,
      3.8831854
    ],
    "Owner": null,
    "Faction": null,
    "FactionRank": 0,
    "OwnerGlobal": null,
    "Health": 0,
    "Count": 0,
    "Lock": 0,
    "Trap": null,
    "Key": null,
    "Soul": null,
    "Charge": 0,
    "Blocked": 0
  },
  {
    "Id": "ex_stronghold_wall00",
    "Translation": [
      38678.254,
      -21552.51,
      1440.0
    ],
    "Rotation": [
      0.0,
      0.0,
      3.8831854
    ],
    "Owner": null,
    "Faction": null,
    "FactionRank": 0,
    "OwnerGlobal": null,
    "Health": 0,
    "Count": 0,
    "Lock": 0,
    "Trap": null,
    "Key": null,
    "Soul": null,
    "Charge": 0,
    "Blocked": 0
  },
  {
    "Id": "ex_stronghold_wall00",
    "Translation": [
      36014.387,
      -18700.111,
      1442.0
    ],
    "Rotation": [
      0.0,
      0.0,
      5.4539824
    ],
    "Owner": null,
    "Faction": null,
    "FactionRank": 0,
    "OwnerGlobal": null,
    "Health": 0,
    "Count": 0,
    "Lock": 0,
    "Trap": null,
    "Key": null,
    "Soul": null,
    "Charge": 0,
    "Blocked": 0
  },
  {
    "Id": "ex_stronghold_wall00",
    "Translation": [
      35239.043,
      -19096.479,
      1442.0
    ],
    "Rotation": [
      0.0,
      0.0,
      3.8831854
    ],
    "Owner": null,
    "Faction": null,
    "FactionRank": 0,
    "OwnerGlobal": null,
    "Health": 0,
    "Count": 0,
    "Lock": 0,
    "Trap": null,
    "Key": null,
    "Soul": null,
    "Charge": 0,
    "Blocked": 0
  },
  {
    "Id": "ex_stronghold_enter00",
    "Translation": [
      37869.105,
      -21614.162,
      1500.0
    ],
    "Rotation": [
      0.0,
      0.0,
      0.74159265
    ],
    "Owner": null,
    "Faction": null,
    "FactionRank": 0,
    "OwnerGlobal": null,
    "Health": 0,
    "Count": 0,
    "Lock": 0,
    "Trap": null,
    "Key": null,
    "Soul": null,
    "Charge": 0,
    "Blocked": 0
  },
  {
    "Id": "ex_stronghold_window00",
    "Translation": [
      35297.34,
      -19086.143,
      1758.0
    ],
    "Rotation": [
      0.0,
      0.0,
      0.74159265
    ],
    "Owner": null,
    "Faction": null,
    "FactionRank": 0,
    "OwnerGlobal": null,
    "Health": 0,
    "Count": 0,
    "Lock": 0,
    "Trap": null,
    "Key": null,
    "Soul": null,
    "Charge": 0,
    "Blocked": 0
  },
  {
    "Id": "ex_stronghold_window00",
    "Translation": [
      35597.92,
      -19290.967,
      1512.0
    ],
    "Rotation": [
      0.0,
      0.0,
      0.74159265
    ],
    "Owner": null,
    "Faction": null,
    "FactionRank": 0,
    "OwnerGlobal": null,
    "Health": 0,
    "Count": 0,
    "Lock": 0,
    "Trap": null,
    "Key": null,
    "Soul": null,
    "Charge": 0,
    "Blocked": 0
  },
  {
    "Id": "ex_stronghold_wall00",
    "Translation": [
      35411.957,
      -18907.709,
      1442.0
    ],
    "Rotation": [
      0.0,
      0.0,
      3.8831854
    ],
    "Owner": null,
    "Faction": null,
    "FactionRank": 0,
    "OwnerGlobal": null,
    "Health": 0,
    "Count": 0,
    "Lock": 0,
    "Trap": null,
    "Key": null,
    "Soul": null,
    "Charge": 0,
    "Blocked": 0
  },
  {
    "Id": "ex_stronghold_wall00",
    "Translation": [
      35584.875,
      -18718.936,
      1442.0
    ],
    "Rotation": [
      0.0,
      0.0,
      3.8831854
    ],
    "Owner": null,
    "Faction": null,
    "FactionRank": 0,
    "OwnerGlobal": null,
    "Health": 0,
    "Count": 0,
    "Lock": 0,
    "Trap": null,
    "Key": null,
    "Soul": null,
    "Charge": 0,
    "Blocked": 0
  },
  {
    "Id": "ex_stronghold_wall01",
    "Translation": [
      35825.613,
      -18527.19,
      1442.0
    ],
    "Rotation": [
      0.0,
      0.0,
      2.3123891
    ],
    "Owner": null,
    "Faction": null,
    "FactionRank": 0,
    "OwnerGlobal": null,
    "Health": 0,
    "Count": 0,
    "Lock": 0,
    "Trap": null,
    "Key": null,
    "Soul": null,
    "Charge": 0,
    "Blocked": 0
  },
  {
    "Id": "ex_stronghold_wall00",
    "Translation": [
      36203.16,
      -18873.025,
      1442.0
    ],
    "Rotation": [
      0.0,
      0.0,
      5.4539824
    ],
    "Owner": null,
    "Faction": null,
    "FactionRank": 0,
    "OwnerGlobal": null,
    "Health": 0,
    "Count": 0,
    "Lock": 0,
    "Trap": null,
    "Key": null,
    "Soul": null,
    "Charge": 0,
    "Blocked": 0
  },
  {
    "Id": "ex_stronghold_wall00",
    "Translation": [
      36391.934,
      -19045.947,
      1442.0
    ],
    "Rotation": [
      0.0,
      0.0,
      5.4539824
    ],
    "Owner": null,
    "Faction": null,
    "FactionRank": 0,
    "OwnerGlobal": null,
    "Health": 0,
    "Count": 0,
    "Lock": 0,
    "Trap": null,
    "Key": null,
    "Soul": null,
    "Charge": 0,
    "Blocked": 0
  },
  {
    "Id": "ex_stronghold_wall00",
    "Translation": [
      36580.71,
      -19218.87,
      1442.0
    ],
    "Rotation": [
      0.0,
      0.0,
      5.4539824
    ],
    "Owner": null,
    "Faction": null,
    "FactionRank": 0,
    "OwnerGlobal": null,
    "Health": 0,
    "Count": 0,
    "Lock": 0,
    "Trap": null,
    "Key": null,
    "Soul": null,
    "Charge": 0,
    "Blocked": 0
  },
  {
    "Id": "ex_stronghold_wall00",
    "Translation": [
      36769.484,
      -19391.783,
      1442.0
    ],
    "Rotation": [
      0.0,
      0.0,
      5.4539824
    ],
    "Owner": null,
    "Faction": null,
    "FactionRank": 0,
    "OwnerGlobal": null,
    "Health": 0,
    "Count": 0,
    "Lock": 0,
    "Trap": null,
    "Key": null,
    "Soul": null,
    "Charge": 0,
    "Blocked": 0
  },
  {
    "Id": "ex_stronghold_pylon01",
    "Translation": [
      37035.996,
      -22081.018,
      1054.0
    ],
    "Rotation": [
      0.0,
      0.0,
      3.8831854
    ],
    "Owner": null,
    "Faction": null,
    "FactionRank": 0,
    "OwnerGlobal": null,
    "Health": 0,
    "Count": 0,
    "Lock": 0,
    "Trap": null,
    "Key": null,
    "Soul": null,
    "Charge": 0,
    "Blocked": 0
  },
  {
    "Id": "ex_stronghold_pylon02",
    "Translation": [
      36280.902,
      -21389.338,
      1054.0
    ],
    "Rotation": [
      0.0,
      0.0,
      3.8831854
    ],
    "Owner": null,
    "Faction": null,
    "FactionRank": 0,
    "OwnerGlobal": null,
    "Health": 0,
    "Count": 0,
    "Lock": 0,
    "Trap": null,
    "Key": null,
    "Soul": null,
    "Charge": 0,
    "Blocked": 0
  },
  {
    "Id": "ex_stronghold_fort01",
    "Translation": [
      35258.87,
      -21841.822,
      1758.0
    ],
    "Rotation": [
      0.0,
      0.0,
      3.8831854
    ],
    "Owner": null,
    "Faction": null,
    "FactionRank": 0,
    "OwnerGlobal": null,
    "Health": 0,
    "Count": 0,
    "Lock": 0,
    "Trap": null,
    "Key": null,
    "Soul": null,
    "Charge": 0,
    "Blocked": 0
  },
  {
    "Id": "ex_stronghold_fort02",
    "Translation": [
      36013.965,
      -22533.498,
      1758.0
    ],
    "Rotation": [
      0.0,
      0.0,
      5.4539824
    ],
    "Owner": null,
    "Faction": null,
    "FactionRank": 0,
    "OwnerGlobal": null,
    "Health": 0,
    "Count": 0,
    "Lock": 0,
    "Trap": null,
    "Key": null,
    "Soul": null,
    "Charge": 0,
    "Blocked": 0
  },
  {
    "Id": "ex_stronghold_wall00",
    "Translation": [
      38252.84,
      -22746.783,
      1440.0
    ],
    "Rotation": [
      0.0,
      0.0,
      3.8831854
    ],
    "Owner": null,
    "Faction": null,
    "FactionRank": 0,
    "OwnerGlobal": null,
    "Health": 0,
    "Count": 0,
    "Lock": 0,
    "Trap": null,
    "Key": null,
    "Soul": null,
    "Charge": 0,
    "Blocked": 0
  },
  {
    "Id": "ex_stronghold_wall00",
    "Translation": [
      38079.914,
      -22935.557,
      1440.0
    ],
    "Rotation": [
      0.0,
      0.0,
      3.8831854
    ],
    "Owner": null,
    "Faction": null,
    "FactionRank": 0,
    "OwnerGlobal": null,
    "Health": 0,
    "Count": 0,
    "Lock": 0,
    "Trap": null,
    "Key": null,
    "Soul": null,
    "Charge": 0,
    "Blocked": 0
  },
  {
    "Id": "ex_stronghold_wall00",
    "Translation": [
      37906.992,
      -23124.33,
      1440.0
    ],
    "Rotation": [
      0.0,
      0.0,
      3.8831854
    ],
    "Owner": null,
    "Faction": null,
    "FactionRank": 0,
    "OwnerGlobal": null,
    "Health": 0,
    "Count": 0,
    "Lock": 0,
    "Trap": null,
    "Key": null,
    "Soul": null,
    "Charge": 0,
    "Blocked": 0
  },
  {
    "Id": "ex_stronghold_wall00",
    "Translation": [
      37734.08,
      -23313.104,
      1440.0
    ],
    "Rotation": [
      0.0,
      0.0,
      3.8831854
    ],
    "Owner": null,
    "Faction": null,
    "FactionRank": 0,
    "OwnerGlobal": null,
    "Health": 0,
    "Count": 0,
    "Lock": 0,
    "Trap": null,
    "Key": null,
    "Soul": null,
    "Charge": 0,
    "Blocked": 0
  },
  {
    "Id": "ex_stronghold_wall00",
    "Translation": [
      37388.246,
      -23690.65,
      1440.0
    ],
    "Rotation": [
      0.0,
      0.0,
      3.8831854
    ],
    "Owner": null,
    "Faction": null,
    "FactionRank": 0,
    "OwnerGlobal": null,
    "Health": 0,
    "Count": 0,
    "Lock": 0,
    "Trap": null,
    "Key": null,
    "Soul": null,
    "Charge": 0,
    "Blocked": 0
  },
  {
    "Id": "ex_stronghold_wall00",
    "Translation": [
      36958.74,
      -23709.479,
      1440.0
    ],
    "Rotation": [
      0.0,
      0.0,
      2.3123891
    ],
    "Owner": null,
    "Faction": null,
    "FactionRank": 0,
    "OwnerGlobal": null,
    "Health": 0,
    "Count": 0,
    "Lock": 0,
    "Trap": null,
    "Key": null,
    "Soul": null,
    "Charge": 0,
    "Blocked": 0
  },
  {
    "Id": "ex_stronghold_wall00",
    "Translation": [
      36769.965,
      -23536.56,
      1440.0
    ],
    "Rotation": [
      0.0,
      0.0,
      2.3123891
    ],
    "Owner": null,
    "Faction": null,
    "FactionRank": 0,
    "OwnerGlobal": null,
    "Health": 0,
    "Count": 0,
    "Lock": 0,
    "Trap": null,
    "Key": null,
    "Soul": null,
    "Charge": 0,
    "Blocked": 0
  },
  {
    "Id": "ex_stronghold_wall00",
    "Translation": [
      36581.19,
      -23363.643,
      1440.0
    ],
    "Rotation": [
      0.0,
      0.0,
      2.3123891
    ],
    "Owner": null,
    "Faction": null,
    "FactionRank": 0,
    "OwnerGlobal": null,
    "Health": 0,
    "Count": 0,
    "Lock": 0,
    "Trap": null,
    "Key": null,
    "Soul": null,
    "Charge": 0,
    "Blocked": 0
  },
  {
    "Id": "ex_stronghold_wall01",
    "Translation": [
      37147.51,
      -23882.4,
      1440.0
    ],
    "Rotation": [
      0.0,
      0.0,
      5.4539824
    ],
    "Owner": null,
    "Faction": null,
    "FactionRank": 0,
    "OwnerGlobal": null,
    "Health": 0,
    "Count": 0,
    "Lock": 0,
    "Trap": null,
    "Key": null,
    "Soul": null,
    "Charge": 0,
    "Blocked": 0
  },
  {
    "Id": "ex_stronghold_wall00",
    "Translation": [
      36392.426,
      -23190.717,
      1440.0
    ],
    "Rotation": [
      0.0,
      0.0,
      2.3123891
    ],
    "Owner": null,
    "Faction": null,
    "FactionRank": 0,
    "OwnerGlobal": null,
    "Health": 0,
    "Count": 0,
    "Lock": 0,
    "Trap": null,
    "Key": null,
    "Soul": null,
    "Charge": 0,
    "Blocked": 0
  },
  {
    "Id": "ex_stronghold_wall00",
    "Translation": [
      36203.652,
      -23017.807,
      1440.0
    ],
    "Rotation": [
      0.0,
      0.0,
      2.3123891
    ],
    "Owner": null,
    "Faction": null,
    "FactionRank": 0,
    "OwnerGlobal": null,
    "Health": 0,
    "Count": 0,
    "Lock": 0,
    "Trap": null,
    "Key": null,
    "Soul": null,
    "Charge": 0,
    "Blocked": 0
  },
  {
    "Id": "ex_stronghold_smdwell00",
    "Translation": [
      35463.504,
      -22376.428,
      2176.0
    ],
    "Rotation": [
      0.0,
      0.0,
      3.8831854
    ],
    "Owner": null,
    "Faction": null,
    "FactionRank": 0,
    "OwnerGlobal": null,
    "Health": 0,
    "Count": 0,
    "Lock": 0,
    "Trap": null,
    "Key": null,
    "Soul": null,
    "Charge": 0,
    "Blocked": 0
  },
  {
    "Id": "ex_stronghold_wall00",
    "Translation": [
      37561.16,
      -23501.877,
      1440.0
    ],
    "Rotation": [
      0.0,
      0.0,
      3.8831854
    ],
    "Owner": null,
    "Faction": null,
    "FactionRank": 0,
    "OwnerGlobal": null,
    "Health": 0,
    "Count": 0,
    "Lock": 0,
    "Trap": null,
    "Key": null,
    "Soul": null,
    "Charge": 0,
    "Blocked": 0
  },
  {
    "Id": "ex_stronghold_enter00",
    "Translation": [
      34511.34,
      -20289.154,
      2206.0
    ],
    "Rotation": [
      0.0,
      0.0,
      2.3123891
    ],
    "Owner": null,
    "Faction": null,
    "FactionRank": 0,
    "OwnerGlobal": null,
    "Health": 0,
    "Count": 0,
    "Lock": 0,
    "Trap": null,
    "Key": null,
    "Soul": null,
    "Charge": 0,
    "Blocked": 0
  },
  {
    "Id": "ex_stronghold_enter00",
    "Translation": [
      35679.65,
      -22140.47,
      2174.0
    ],
    "Rotation": [
      0.0,
      0.0,
      2.3123891
    ],
    "Owner": null,
    "Faction": null,
    "FactionRank": 0,
    "OwnerGlobal": null,
    "Health": 0,
    "Count": 0,
    "Lock": 0,
    "Trap": null,
    "Key": null,
    "Soul": null,
    "Charge": 0,
    "Blocked": 0
  },
  {
    "Id": "ex_stronghold_enter00",
    "Translation": [
      35647.76,
      -20896.162,
      1502.0
    ],
    "Rotation": [
      0.0,
      0.0,
      2.3123891
    ],
    "Owner": null,
    "Faction": null,
    "FactionRank": 0,
    "OwnerGlobal": null,
    "Health": 0,
    "Count": 0,
    "Lock": 0,
    "Trap": null,
    "Key": null,
    "Soul": null,
    "Charge": 0,
    "Blocked": 0
  },
  {
    "Id": "ex_stronghold_window00",
    "Translation": [
      36295.984,
      -21668.959,
      1518.0
    ],
    "Rotation": [
      0.0,
      0.0,
      0.74159265
    ],
    "Owner": null,
    "Faction": null,
    "FactionRank": 0,
    "OwnerGlobal": null,
    "Health": 0,
    "Count": 0,
    "Lock": 0,
    "Trap": null,
    "Key": null,
    "Soul": null,
    "Charge": 0,
    "Blocked": 0
  },
  {
    "Id": "ex_stronghold_window00",
    "Translation": [
      36011.3,
      -21406.822,
      1514.0
    ],
    "Rotation": [
      0.0,
      0.0,
      0.74159265
    ],
    "Owner": null,
    "Faction": null,
    "FactionRank": 0,
    "OwnerGlobal": null,
    "Health": 0,
    "Count": 0,
    "Lock": 0,
    "Trap": null,
    "Key": null,
    "Soul": null,
    "Charge": 0,
    "Blocked": 0
  },
  {
    "Id": "ex_stronghold_window00",
    "Translation": [
      36196.42,
      -22917.607,
      1758.0
    ],
    "Rotation": [
      0.0,
      0.0,
      2.3123891
    ],
    "Owner": null,
    "Faction": null,
    "FactionRank": 0,
    "OwnerGlobal": null,
    "Health": 0,
    "Count": 0,
    "Lock": 0,
    "Trap": null,
    "Key": null,
    "Soul": null,
    "Charge": 0,
    "Blocked": 0
  },
  {
    "Id": "ex_stronghold_window00",
    "Translation": [
      36456.2,
      -22708.049,
      1523.0
    ],
    "Rotation": [
      0.0,
      0.0,
      2.3123891
    ],
    "Owner": null,
    "Faction": null,
    "FactionRank": 0,
    "OwnerGlobal": null,
    "Health": 0,
    "Count": 0,
    "Lock": 0,
    "Trap": null,
    "Key": null,
    "Soul": null,
    "Charge": 0,
    "Blocked": 0
  },
  {
    "Id": "ex_stronghold_window00",
    "Translation": [
      36107.49,
      -21566.814,
      1755.0
    ],
    "Rotation": [
      0.0,
      0.0,
      0.74159265
    ],
    "Owner": null,
    "Faction": null,
    "FactionRank": 0,
    "OwnerGlobal": null,
    "Health": 0,
    "Count": 0,
    "Lock": 0,
    "Trap": null,
    "Key": null,
    "Soul": null,
    "Charge": 0,
    "Blocked": 0
  },
  {
    "Id": "ex_stronghold_window00",
    "Translation": [
      35499.12,
      -20266.377,
      1751.0
    ],
    "Rotation": [
      0.0,
      0.0,
      2.3123891
    ],
    "Owner": null,
    "Faction": null,
    "FactionRank": 0,
    "OwnerGlobal": null,
    "Health": 0,
    "Count": 0,
    "Lock": 0,
    "Trap": null,
    "Key": null,
    "Soul": null,
    "Charge": 0,
    "Blocked": 0
  },
  {
    "Id": "ex_stronghold_window00",
    "Translation": [
      35536.055,
      -20301.56,
      1519.0
    ],
    "Rotation": [
      0.0,
      0.0,
      2.3123891
    ],
    "Owner": null,
    "Faction": null,
    "FactionRank": 0,
    "OwnerGlobal": null,
    "Health": 0,
    "Count": 0,
    "Lock": 0,
    "Trap": null,
    "Key": null,
    "Soul": null,
    "Charge": 0,
    "Blocked": 0
  },
  {
    "Id": "ex_stronghold_window00",
    "Translation": [
      34429.598,
      -19134.791,
      1755.0
    ],
    "Rotation": [
      0.0,
      0.0,
      5.4539824
    ],
    "Owner": null,
    "Faction": null,
    "FactionRank": 0,
    "OwnerGlobal": null,
    "Health": 0,
    "Count": 0,
    "Lock": 0,
    "Trap": null,
    "Key": null,
    "Soul": null,
    "Charge": 0,
    "Blocked": 0
  },
  {
    "Id": "ex_stronghold_window00",
    "Translation": [
      33885.95,
      -19649.83,
      1510.0
    ],
    "Rotation": [
      0.0,
      0.0,
      5.4539824
    ],
    "Owner": null,
    "Faction": null,
    "FactionRank": 0,
    "OwnerGlobal": null,
    "Health": 0,
    "Count": 0,
    "Lock": 0,
    "Trap": null,
    "Key": null,
    "Soul": null,
    "Charge": 0,
    "Blocked": 0
  },
  {
    "Id": "ex_stronghold_window00",
    "Translation": [
      33397.16,
      -20189.354,
      1521.0
    ],
    "Rotation": [
      0.0,
      0.0,
      5.4539824
    ],
    "Owner": null,
    "Faction": null,
    "FactionRank": 0,
    "OwnerGlobal": null,
    "Health": 0,
    "Count": 0,
    "Lock": 0,
    "Trap": null,
    "Key": null,
    "Soul": null,
    "Charge": 0,
    "Blocked": 0
  },
  {
    "Id": "ex_stronghold_window00",
    "Translation": [
      33569.188,
      -20077.057,
      1758.0
    ],
    "Rotation": [
      0.0,
      0.0,
      5.4539824
    ],
    "Owner": null,
    "Faction": null,
    "FactionRank": 0,
    "OwnerGlobal": null,
    "Health": 0,
    "Count": 0,
    "Lock": 0,
    "Trap": null,
    "Key": null,
    "Soul": null,
    "Charge": 0,
    "Blocked": 0
  },
  {
    "Id": "ex_stronghold_window00",
    "Translation": [
      34174.895,
      -19411.38,
      1753.0
    ],
    "Rotation": [
      0.0,
      0.0,
      5.4539824
    ],
    "Owner": null,
    "Faction": null,
    "FactionRank": 0,
    "OwnerGlobal": null,
    "Health": 0,
    "Count": 0,
    "Lock": 0,
    "Trap": null,
    "Key": null,
    "Soul": null,
    "Charge": 0,
    "Blocked": 0
  },
  {
    "Id": "ex_stronghold_window00",
    "Translation": [
      35260.496,
      -22960.76,
      1535.0
    ],
    "Rotation": [
      0.0,
      0.0,
      3.8831854
    ],
    "Owner": null,
    "Faction": null,
    "FactionRank": 0,
    "OwnerGlobal": null,
    "Health": 0,
    "Count": 0,
    "Lock": 0,
    "Trap": null,
    "Key": null,
    "Soul": null,
    "Charge": 0,
    "Blocked": 0
  },
  {
    "Id": "ex_stronghold_window00",
    "Translation": [
      33404.605,
      -21263.443,
      1526.0
    ],
    "Rotation": [
      0.0,
      0.0,
      3.8831854
    ],
    "Owner": null,
    "Faction": null,
    "FactionRank": 0,
    "OwnerGlobal": null,
    "Health": 0,
    "Count": 0,
    "Lock": 0,
    "Trap": null,
    "Key": null,
    "Soul": null,
    "Charge": 0,
    "Blocked": 0
  },
  {
    "Id": "ex_stronghold_window00",
    "Translation": [
      34488.637,
      -22257.799,
      1522.0
    ],
    "Rotation": [
      0.0,
      0.0,
      3.8831854
    ],
    "Owner": null,
    "Faction": null,
    "FactionRank": 0,
    "OwnerGlobal": null,
    "Health": 0,
    "Count": 0,
    "Lock": 0,
    "Trap": null,
    "Key": null,
    "Soul": null,
    "Charge": 0,
    "Blocked": 0
  },
  {
    "Id": "ex_stronghold_window00",
    "Translation": [
      34867.535,
      -22602.15,
      1532.0
    ],
    "Rotation": [
      0.0,
      0.0,
      3.8831854
    ],
    "Owner": null,
    "Faction": null,
    "FactionRank": 0,
    "OwnerGlobal": null,
    "Health": 0,
    "Count": 0,
    "Lock": 0,
    "Trap": null,
    "Key": null,
    "Soul": null,
    "Charge": 0,
    "Blocked": 0
  },
  {
    "Id": "ex_stronghold_window00",
    "Translation": [
      34074.01,
      -21808.83,
      1758.0
    ],
    "Rotation": [
      0.0,
      0.0,
      3.8831854
    ],
    "Owner": null,
    "Faction": null,
    "FactionRank": 0,
    "OwnerGlobal": null,
    "Health": 0,
    "Count": 0,
    "Lock": 0,
    "Trap": null,
    "Key": null,
    "Soul": null,
    "Charge": 0,
    "Blocked": 0
  },
  {
    "Id": "ex_stronghold_pylon00",
    "Translation": [
      34110.027,
      -19400.775,
      1054.0
    ],
    "Rotation": [
      0.0,
      0.0,
      3.8831854
    ],
    "Owner": null,
    "Faction": null,
    "FactionRank": 0,
    "OwnerGlobal": null,
    "Health": 0,
    "Count": 0,
    "Lock": 0,
    "Trap": null,
    "Key": null,
    "Soul": null,
    "Charge": 0,
    "Blocked": 0
  },
  {
    "Id": "ex_stronghold_pylon01",
    "Translation": [
      35337.043,
      -20524.748,
      1054.0
    ],
    "Rotation": [
      0.0,
      0.0,
      3.8831854
    ],
    "Owner": null,
    "Faction": null,
    "FactionRank": 0,
    "OwnerGlobal": null,
    "Health": 0,
    "Count": 0,
    "Lock": 0,
    "Trap": null,
    "Key": null,
    "Soul": null,
    "Charge": 0,
    "Blocked": 0
  },
  {
    "Id": "ex_stronghold_fort00",
    "Translation": [
      34464.15,
      -20245.916,
      1758.0
    ],
    "Rotation": [
      0.0,
      0.0,
      5.4539824
    ],
    "Owner": null,
    "Faction": null,
    "FactionRank": 0,
    "OwnerGlobal": null,
    "Health": 0,
    "Count": 0,
    "Lock": 0,
    "Trap": null,
    "Key": null,
    "Soul": null,
    "Charge": 0,
    "Blocked": 0
  },
  {
    "Id": "ex_stronghold_dome00",
    "Translation": [
      34122.28,
      -20713.885,
      2334.0
    ],
    "Rotation": [
      0.0,
      0.0,
      3.0977874
    ],
    "Owner": null,
    "Faction": null,
    "FactionRank": 0,
    "OwnerGlobal": null,
    "Health": 0,
    "Count": 0,
    "Lock": 0,
    "Trap": null,
    "Key": null,
    "Soul": null,
    "Charge": 0,
    "Blocked": 0
  },
  {
    "Id": "ex_stronghold_pylon00",
    "Translation": [
      38263.01,
      -23204.982,
      1054.0
    ],
    "Rotation": [
      0.0,
      0.0,
      0.74159265
    ],
    "Owner": null,
    "Faction": null,
    "FactionRank": 0,
    "OwnerGlobal": null,
    "Health": 0,
    "Count": 0,
    "Lock": 0,
    "Trap": null,
    "Key": null,
    "Soul": null,
    "Charge": 0,
    "Blocked": 0
  },
  {
    "Id": "ex_stronghold_window00",
    "Translation": [
      34297.555,
      -19230.453,
      1523.4132
    ],
    "Rotation": [
      0.0,
      0.0,
      5.2539825
    ],
    "Owner": null,
    "Faction": null,
    "FactionRank": 0,
    "OwnerGlobal": null,
    "Health": 0,
    "Count": 0,
    "Lock": 0,
    "Trap": null,
    "Key": null,
    "Soul": null,
    "Charge": 0,
    "Blocked": 0
  },
  {
    "Id": "ex_stronghold_window00",
    "Translation": [
      34522.35,
      -22219.506,
      1758.0
    ],
    "Rotation": [
      0.0,
      0.0,
      3.8831854
    ],
    "Owner": null,
    "Faction": null,
    "FactionRank": 0,
    "OwnerGlobal": null,
    "Health": 0,
    "Count": 0,
    "Lock": 0,
    "Trap": null,
    "Key": null,
    "Soul": null,
    "Charge": 0,
    "Blocked": 0
  },
  {
    "Id": "ex_stronghold_window00",
    "Translation": [
      34029.18,
      -21835.564,
      1527.0
    ],
    "Rotation": [
      0.0,
      0.0,
      3.8831854
    ],
    "Owner": null,
    "Faction": null,
    "FactionRank": 0,
    "OwnerGlobal": null,
    "Health": 0,
    "Count": 0,
    "Lock": 0,
    "Trap": null,
    "Key": null,
    "Soul": null,
    "Charge": 0,
    "Blocked": 0
  },
  {
    "Id": "flora_ashtree_03",
    "Translation": [
      40793.203,
      -23682.63,
      1177.2654
    ],
    "Rotation": [
      0.0,
      0.0,
      4.1831875
    ],
    "Owner": null,
    "Faction": null,
    "FactionRank": 0,
    "OwnerGlobal": null,
    "Health": 0,
    "Count": 0,
    "Lock": 0,
    "Trap": null,
    "Key": null,
    "Soul": null,
    "Charge": 0,
    "Blocked": 0
  },
  {
    "Id": "Flora_ashtree_01",
    "Translation": [
      33434.543,
      -16455.414,
      809.589
    ],
    "Rotation": [
      0.0,
      0.0,
      5.483186
    ],
    "Owner": null,
    "Faction": null,
    "FactionRank": 0,
    "OwnerGlobal": null,
    "Health": 0,
    "Count": 0,
    "Lock": 0,
    "Trap": null,
    "Key": null,
    "Soul": null,
    "Charge": 0,
    "Blocked": 0
  },
  {
    "Id": "terrain_rock_ma_53",
    "Translation": [
      35341.332,
      -16611.352,
      571.5403
    ],
    "Rotation": [
      0.0,
      0.0,
      5.183188
    ],
    "Owner": null,
    "Faction": null,
    "FactionRank": 0,
    "OwnerGlobal": null,
    "Health": 0,
    "Count": 0,
    "Lock": 0,
    "Trap": null,
    "Key": null,
    "Soul": null,
    "Charge": 0,
    "Blocked": 0
  },
  {
    "Id": "terrain_rock_ma_07",
    "Translation": [
      35405.945,
      -16784.39,
      691.6582
    ],
    "Rotation": [
      0.0,
      0.0,
      2.0831869
    ],
    "Owner": null,
    "Faction": null,
    "FactionRank": 0,
    "OwnerGlobal": null,
    "Health": 0,
    "Count": 0,
    "Lock": 0,
    "Trap": null,
    "Key": null,
    "Soul": null,
    "Charge": 0,
    "Blocked": 0
  },
  {
    "Id": "terrain_ma_rock_13",
    "Translation": [
      35240.906,
      -16582.553,
      503.74295
    ],
    "Rotation": [
      0.0,
      0.0,
      3.4836771
    ],
    "Owner": null,
    "Faction": null,
    "FactionRank": 0,
    "OwnerGlobal": null,
    "Health": 0,
    "Count": 0,
    "Lock": 0,
    "Trap": null,
    "Key": null,
    "Soul": null,
    "Charge": 0,
    "Blocked": 0
  },
  {
    "Id": "terrain_rock_ma_07",
    "Translation": [
      35030.094,
      -16921.031,
      634.3449
    ],
    "Rotation": [
      0.0,
      0.0,
      2.9831865
    ],
    "Owner": null,
    "Faction": null,
    "FactionRank": 0,
    "OwnerGlobal": null,
    "Health": 0,
    "Count": 0,
    "Lock": 0,
    "Trap": null,
    "Key": null,
    "Soul": null,
    "Charge": 0,
    "Blocked": 0
  },
  {
    "Id": "terrain_rock_ma_53",
    "Translation": [
      39424.277,
      -18821.34,
      405.0984
    ],
    "Rotation": [
      0.0,
      0.0,
      3.883187
    ],
    "Owner": null,
    "Faction": null,
    "FactionRank": 0,
    "OwnerGlobal": null,
    "Health": 0,
    "Count": 0,
    "Lock": 0,
    "Trap": null,
    "Key": null,
    "Soul": null,
    "Charge": 0,
    "Blocked": 0
  },
  {
    "Id": "terrain_rock_ma_07",
    "Translation": [
      39584.465,
      -18778.514,
      316.39532
    ],
    "Rotation": [
      0.0,
      0.0,
      4.583187
    ],
    "Owner": null,
    "Faction": null,
    "FactionRank": 0,
    "OwnerGlobal": null,
    "Health": 0,
    "Count": 0,
    "Lock": 0,
    "Trap": null,
    "Key": null,
    "Soul": null,
    "Charge": 0,
    "Blocked": 0
  },
  {
    "Id": "terrain_ma_rock_13",
    "Translation": [
      39816.89,
      -19809.523,
      990.96094
    ],
    "Rotation": [
      0.0,
      0.0,
      1.0
    ],
    "Owner": null,
    "Faction": null,
    "FactionRank": 0,
    "OwnerGlobal": null,
    "Health": 0,
    "Count": 0,
    "Lock": 0,
    "Trap": null,
    "Key": null,
    "Soul": null,
    "Charge": 0,
    "Blocked": 0
  },
  {
    "Id": "terrain_rock_ma_58",
    "Translation": [
      37084.94,
      -17908.824,
      730.83655
    ],
    "Rotation": [
      6.1831856,
      5.883186,
      4.383186
    ],
    "Owner": null,
    "Faction": null,
    "FactionRank": 0,
    "OwnerGlobal": null,
    "Health": 0,
    "Count": 0,
    "Lock": 0,
    "Trap": null,
    "Key": null,
    "Soul": null,
    "Charge": 0,
    "Blocked": 0
  },
  {
    "Id": "terrain_rock_ma_07",
    "Translation": [
      37120.145,
      -18220.553,
      873.45905
    ],
    "Rotation": [
      0.0,
      0.0,
      5.983185
    ],
    "Owner": null,
    "Faction": null,
    "FactionRank": 0,
    "OwnerGlobal": null,
    "Health": 0,
    "Count": 0,
    "Lock": 0,
    "Trap": null,
    "Key": null,
    "Soul": null,
    "Charge": 0,
    "Blocked": 0
  },
  {
    "Id": "terrain_ma_rock_13",
    "Translation": [
      37376.055,
      -18057.691,
      834.1077
    ],
    "Rotation": [
      5.983186,
      5.883186,
      1.3000008
    ],
    "Owner": null,
    "Faction": null,
    "FactionRank": 0,
    "OwnerGlobal": null,
    "Health": 0,
    "Count": 0,
    "Lock": 0,
    "Trap": null,
    "Key": null,
    "Soul": null,
    "Charge": 0,
    "Blocked": 0
  },
  {
    "Id": "terrain_rock_ma_53",
    "Translation": [
      39678.156,
      -19739.645,
      1057.5768
    ],
    "Rotation": [
      0.0,
      0.0,
      3.8831882
    ],
    "Owner": null,
    "Faction": null,
    "FactionRank": 0,
    "OwnerGlobal": null,
    "Health": 0,
    "Count": 0,
    "Lock": 0,
    "Trap": null,
    "Key": null,
    "Soul": null,
    "Charge": 0,
    "Blocked": 0
  },
  {
    "Id": "terrain_rock_ma_02",
    "Translation": [
      37622.387,
      -18546.713,
      913.8458
    ],
    "Rotation": [
      0.0,
      6.2831855,
      4.083186
    ],
    "Owner": null,
    "Faction": null,
    "FactionRank": 0,
    "OwnerGlobal": null,
    "Health": 0,
    "Count": 0,
    "Lock": 0,
    "Trap": null,
    "Key": null,
    "Soul": null,
    "Charge": 0,
    "Blocked": 0
  },
  {
    "Id": "terrain_ma_rock_13",
    "Translation": [
      39699.56,
      -18822.33,
      427.40652
    ],
    "Rotation": [
      0.0,
      0.0,
      4.683187
    ],
    "Owner": null,
    "Faction": null,
    "FactionRank": 0,
    "OwnerGlobal": null,
    "Health": 0,
    "Count": 0,
    "Lock": 0,
    "Trap": null,
    "Key": null,
    "Soul": null,
    "Charge": 0,
    "Blocked": 0
  },
  {
    "Id": "terrain_rock_ma_53",
    "Translation": [
      37822.832,
      -19011.95,
      781.42175
    ],
    "Rotation": [
      0.0,
      0.0,
      3.7831862
    ],
    "Owner": null,
    "Faction": null,
    "FactionRank": 0,
    "OwnerGlobal": null,
    "Health": 0,
    "Count": 0,
    "Lock": 0,
    "Trap": null,
    "Key": null,
    "Soul": null,
    "Charge": 0,
    "Blocked": 0
  },
  {
    "Id": "terrain_rock_ma_07",
    "Translation": [
      37593.37,
      -18713.049,
      682.48486
    ],
    "Rotation": [
      0.0,
      0.0,
      3.9831858
    ],
    "Owner": null,
    "Faction": null,
    "FactionRank": 0,
    "OwnerGlobal": null,
    "Health": 0,
    "Count": 0,
    "Lock": 0,
    "Trap": null,
    "Key": null,
    "Soul": null,
    "Charge": 0,
    "Blocked": 0
  },
  {
    "Id": "terrain_ma_rock_13",
    "Translation": [
      37756.59,
      -18655.23,
      830.7361
    ],
    "Rotation": [
      0.0,
      0.0,
      2.2999992
    ],
    "Owner": null,
    "Faction": null,
    "FactionRank": 0,
    "OwnerGlobal": null,
    "Health": 0,
    "Count": 0,
    "Lock": 0,
    "Trap": null,
    "Key": null,
    "Soul": null,
    "Charge": 0,
    "Blocked": 0
  },
  {
    "Id": "terrain_rock_ma_07",
    "Translation": [
      40108.25,
      -18825.006,
      527.3167
    ],
    "Rotation": [
      0.0,
      0.0,
      6.083185
    ],
    "Owner": null,
    "Faction": null,
    "FactionRank": 0,
    "OwnerGlobal": null,
    "Health": 0,
    "Count": 0,
    "Lock": 0,
    "Trap": null,
    "Key": null,
    "Soul": null,
    "Charge": 0,
    "Blocked": 0
  },
  {
    "Id": "terrain_rock_ma_07",
    "Translation": [
      40008.92,
      -18590.064,
      310.4875
    ],
    "Rotation": [
      0.0,
      0.0,
      3.5663722
    ],
    "Owner": null,
    "Faction": null,
    "FactionRank": 0,
    "OwnerGlobal": null,
    "Health": 0,
    "Count": 0,
    "Lock": 0,
    "Trap": null,
    "Key": null,
    "Soul": null,
    "Charge": 0,
    "Blocked": 0
  },
  {
    "Id": "terrain_ma_rock13",
    "Translation": [
      40243.31,
      -18935.48,
      566.3203
    ],
    "Rotation": [
      0.0,
      0.099999554,
      3.783187
    ],
    "Owner": null,
    "Faction": null,
    "FactionRank": 0,
    "OwnerGlobal": null,
    "Health": 0,
    "Count": 0,
    "Lock": 0,
    "Trap": null,
    "Key": null,
    "Soul": null,
    "Charge": 0,
    "Blocked": 0
  },
  {
    "Id": "flora_ash_grass_w_01",
    "Translation": [
      39797.996,
      -18632.305,
      429.1893
    ],
    "Rotation": [
      6.1837015,
      0.0,
      4.783186
    ],
    "Owner": null,
    "Faction": null,
    "FactionRank": 0,
    "OwnerGlobal": null,
    "Health": 0,
    "Count": 0,
    "Lock": 0,
    "Trap": null,
    "Key": null,
    "Soul": null,
    "Charge": 0,
    "Blocked": 0
  },
  {
    "Id": "flora_ash_grass_b_01",
    "Translation": [
      39741.676,
      -18536.43,
      375.76303
    ],
    "Rotation": [
      0.0,
      0.0,
      5.383186
    ],
    "Owner": null,
    "Faction": null,
    "FactionRank": 0,
    "OwnerGlobal": null,
    "Health": 0,
    "Count": 0,
    "Lock": 0,
    "Trap": null,
    "Key": null,
    "Soul": null,
    "Charge": 0,
    "Blocked": 0
  },
  {
    "Id": "flora_ash_grass_w_01",
    "Translation": [
      39753.81,
      -18346.396,
      323.3897
    ],
    "Rotation": [
      6.1837015,
      0.0,
      4.6831865
    ],
    "Owner": null,
    "Faction": null,
    "FactionRank": 0,
    "OwnerGlobal": null,
    "Health": 0,
    "Count": 0,
    "Lock": 0,
    "Trap": null,
    "Key": null,
    "Soul": null,
    "Charge": 0,
    "Blocked": 0
  },
  {
    "Id": "flora_ash_grass_w_01",
    "Translation": [
      39857.777,
      -18496.838,
      381.79327
    ],
    "Rotation": [
      6.1837015,
      0.0,
      5.8831854
    ],
    "Owner": null,
    "Faction": null,
    "FactionRank": 0,
    "OwnerGlobal": null,
    "Health": 0,
    "Count": 0,
    "Lock": 0,
    "Trap": null,
    "Key": null,
    "Soul": null,
    "Charge": 0,
    "Blocked": 0
  },
  {
    "Id": "terrain_ma_rock13",
    "Translation": [
      40415.723,
      -18911.596,
      491.46133
    ],
    "Rotation": [
      0.01681406,
      0.0,
      6.183185
    ],
    "Owner": null,
    "Faction": null,
    "FactionRank": 0,
    "OwnerGlobal": null,
    "Health": 0,
    "Count": 0,
    "Lock": 0,
    "Trap": null,
    "Key": null,
    "Soul": null,
    "Charge": 0,
    "Blocked": 0
  },
  {
    "Id": "flora_ash_grass_w_01",
    "Translation": [
      39948.457,
      -18701.207,
      427.80234
    ],
    "Rotation": [
      0.0,
      0.0,
      0.1
    ],
    "Owner": null,
    "Faction": null,
    "FactionRank": 0,
    "OwnerGlobal": null,
    "Health": 0,
    "Count": 0,
    "Lock": 0,
    "Trap": null,
    "Key": null,
    "Soul": null,
    "Charge": 0,
    "Blocked": 0
  },
  {
    "Id": "flora_ash_grass_b_01",
    "Translation": [
      39662.78,
      -18361.102,
      341.05713
    ],
    "Rotation": [
      0.0,
      0.0,
      5.383186
    ],
    "Owner": null,
    "Faction": null,
    "FactionRank": 0,
    "OwnerGlobal": null,
    "Health": 0,
    "Count": 0,
    "Lock": 0,
    "Trap": null,
    "Key": null,
    "Soul": null,
    "Charge": 0,
    "Blocked": 0
  },
  {
    "Id": "terrain_rock_ma_550",
    "Translation": [
      40199.582,
      -19122.535,
      621.38556
    ],
    "Rotation": [
      0.0,
      0.0,
      5.583186
    ],
    "Owner": null,
    "Faction": null,
    "FactionRank": 0,
    "OwnerGlobal": null,
    "Health": 0,
    "Count": 0,
    "Lock": 0,
    "Trap": null,
    "Key": null,
    "Soul": null,
    "Charge": 0,
    "Blocked": 0
  },
  {
    "Id": "terrain_rock_ma_57",
    "Translation": [
      32906.504,
      -17234.146,
      1034.7195
    ],
    "Rotation": [
      0.0,
      0.0,
      4.583187
    ],
    "Owner": null,
    "Faction": null,
    "FactionRank": 0,
    "OwnerGlobal": null,
    "Health": 0,
    "Count": 0,
    "Lock": 0,
    "Trap": null,
    "Key": null,
    "Soul": null,
    "Charge": 0,
    "Blocked": 0
  },
  {
    "Id": "Flora_ashtree_01",
    "Translation": [
      40601.895,
      -23990.156,
      1025.7064
    ],
    "Rotation": [
      0.0,
      0.0,
      5.4831853
    ],
    "Owner": null,
    "Faction": null,
    "FactionRank": 0,
    "OwnerGlobal": null,
    "Health": 0,
    "Count": 0,
    "Lock": 0,
    "Trap": null,
    "Key": null,
    "Soul": null,
    "Charge": 0,
    "Blocked": 0
  },
  {
    "Id": "flora_ash_log_01",
    "Translation": [
      40674.188,
      -23726.357,
      924.1295
    ],
    "Rotation": [
      0.0,
      0.0,
      3.7831864
    ],
    "Owner": null,
    "Faction": null,
    "FactionRank": 0,
    "OwnerGlobal": null,
    "Health": 0,
    "Count": 0,
    "Lock": 0,
    "Trap": null,
    "Key": null,
    "Soul": null,
    "Charge": 0,
    "Blocked": 0
  },
  {
    "Id": "flora_ashtree_05",
    "Translation": [
      40612.906,
      -23898.076,
      1391.5164
    ],
    "Rotation": [
      0.0,
      0.0,
      5.683186
    ],
    "Owner": null,
    "Faction": null,
    "FactionRank": 0,
    "OwnerGlobal": null,
    "Health": 0,
    "Count": 0,
    "Lock": 0,
    "Trap": null,
    "Key": null,
    "Soul": null,
    "Charge": 0,
    "Blocked": 0
  },
  {
    "Id": "flora_ash_grass_b_01",
    "Translation": [
      39600.35,
      -24397.568,
      762.4605
    ],
    "Rotation": [
      0.0,
      6.1831856,
      5.283187
    ],
    "Owner": null,
    "Faction": null,
    "FactionRank": 0,
    "OwnerGlobal": null,
    "Health": 0,
    "Count": 0,
    "Lock": 0,
    "Trap": null,
    "Key": null,
    "Soul": null,
    "Charge": 0,
    "Blocked": 0
  },
  {
    "Id": "flora_ash_grass_b_01",
    "Translation": [
      39722.832,
      -24533.393,
      768.95197
    ],
    "Rotation": [
      0.5,
      0.0,
      4.6831865
    ],
    "Owner": null,
    "Faction": null,
    "FactionRank": 0,
    "OwnerGlobal": null,
    "Health": 0,
    "Count": 0,
    "Lock": 0,
    "Trap": null,
    "Key": null,
    "Soul": null,
    "Charge": 0,
    "Blocked": 0
  },
  {
    "Id": "flora_ash_grass_b_01",
    "Translation": [
      39083.645,
      -19235.182,
      694.4815
    ],
    "Rotation": [
      0.3,
      0.0,
      4.483186
    ],
    "Owner": null,
    "Faction": null,
    "FactionRank": 0,
    "OwnerGlobal": null,
    "Health": 0,
    "Count": 0,
    "Lock": 0,
    "Trap": null,
    "Key": null,
    "Soul": null,
    "Charge": 0,
    "Blocked": 0
  },
  {
    "Id": "flora_ash_grass_b_01",
    "Translation": [
      39162.27,
      -19066.756,
      597.9482
    ],
    "Rotation": [
      0.0,
      0.0,
      4.483186
    ],
    "Owner": null,
    "Faction": null,
    "FactionRank": 0,
    "OwnerGlobal": null,
    "Health": 0,
    "Count": 0,
    "Lock": 0,
    "Trap": null,
    "Key": null,
    "Soul": null,
    "Charge": 0,
    "Blocked": 0
  },
  {
    "Id": "flora_ash_grass_b_01",
    "Translation": [
      39151.98,
      -19311.44,
      732.89886
    ],
    "Rotation": [
      0.0,
      0.0,
      3.8831863
    ],
    "Owner": null,
    "Faction": null,
    "FactionRank": 0,
    "OwnerGlobal": null,
    "Health": 0,
    "Count": 0,
    "Lock": 0,
    "Trap": null,
    "Key": null,
    "Soul": null,
    "Charge": 0,
    "Blocked": 0
  },
  {
    "Id": "flora_ash_grass_b_01",
    "Translation": [
      39169.793,
      -19232.207,
      673.961
    ],
    "Rotation": [
      0.5,
      0.0,
      3.8831863
    ],
    "Owner": null,
    "Faction": null,
    "FactionRank": 0,
    "OwnerGlobal": null,
    "Health": 0,
    "Count": 0,
    "Lock": 0,
    "Trap": null,
    "Key": null,
    "Soul": null,
    "Charge": 0,
    "Blocked": 0
  },
  {
    "Id": "flora_ash_grass_b_01",
    "Translation": [
      37319.39,
      -18255.299,
      884.52594
    ],
    "Rotation": [
      5.783186,
      5.883186,
      4.982324
    ],
    "Owner": null,
    "Faction": null,
    "FactionRank": 0,
    "OwnerGlobal": null,
    "Health": 0,
    "Count": 0,
    "Lock": 0,
    "Trap": null,
    "Key": null,
    "Soul": null,
    "Charge": 0,
    "Blocked": 0
  },
  {
    "Id": "flora_ash_grass_b_01",
    "Translation": [
      37395.113,
      -18203.545,
      861.30286
    ],
    "Rotation": [
      0.0,
      0.0,
      4.083186
    ],
    "Owner": null,
    "Faction": null,
    "FactionRank": 0,
    "OwnerGlobal": null,
    "Health": 0,
    "Count": 0,
    "Lock": 0,
    "Trap": null,
    "Key": null,
    "Soul": null,
    "Charge": 0,
    "Blocked": 0
  },
  {
    "Id": "flora_ash_grass_b_01",
    "Translation": [
      37797.285,
      -18764.545,
      867.23944
    ],
    "Rotation": [
      0.0,
      0.0,
      3.4831865
    ],
    "Owner": null,
    "Faction": null,
    "FactionRank": 0,
    "OwnerGlobal": null,
    "Health": 0,
    "Count": 0,
    "Lock": 0,
    "Trap": null,
    "Key": null,
    "Soul": null,
    "Charge": 0,
    "Blocked": 0
  },
  {
    "Id": "flora_ash_grass_b_01",
    "Translation": [
      37831.85,
      -18745.363,
      862.6031
    ],
    "Rotation": [
      0.1,
      0.0,
      4.8831863
    ],
    "Owner": null,
    "Faction": null,
    "FactionRank": 0,
    "OwnerGlobal": null,
    "Health": 0,
    "Count": 0,
    "Lock": 0,
    "Trap": null,
    "Key": null,
    "Soul": null,
    "Charge": 0,
    "Blocked": 0
  },
  {
    "Id": "Flora_Ash_Grass_R_01",
    "Translation": [
      39788.773,
      -19667.764,
      1089.5085
    ],
    "Rotation": [
      0.4,
      0.0,
      0.30000007
    ],
    "Owner": null,
    "Faction": null,
    "FactionRank": 0,
    "OwnerGlobal": null,
    "Health": 0,
    "Count": 0,
    "Lock": 0,
    "Trap": null,
    "Key": null,
    "Soul": null,
    "Charge": 0,
    "Blocked": 0
  },
  {
    "Id": "Flora_ashtree_01",
    "Translation": [
      37028.4,
      -18107.387,
      1013.5736
    ],
    "Rotation": [
      0.0,
      0.0,
      5.2831864
    ],
    "Owner": null,
    "Faction": null,
    "FactionRank": 0,
    "OwnerGlobal": null,
    "Health": 0,
    "Count": 0,
    "Lock": 0,
    "Trap": null,
    "Key": null,
    "Soul": null,
    "Charge": 0,
    "Blocked": 0
  },
  {
    "Id": "flora_ashtree_06",
    "Translation": [
      39614.324,
      -19956.326,
      1347.7386
    ],
    "Rotation": [
      0.0,
      0.0,
      5.783186
    ],
    "Owner": null,
    "Faction": null,
    "FactionRank": 0,
    "OwnerGlobal": null,
    "Health": 0,
    "Count": 0,
    "Lock": 0,
    "Trap": null,
    "Key": null,
    "Soul": null,
    "Charge": 0,
    "Blocked": 0
  },
  {
    "Id": "terrain_ma_rock_13",
    "Translation": [
      37294.28,
      -18112.959,
      852.0586
    ],
    "Rotation": [
      0.0,
      0.0,
      0.2
    ],
    "Owner": null,
    "Faction": null,
    "FactionRank": 0,
    "OwnerGlobal": null,
    "Health": 0,
    "Count": 0,
    "Lock": 0,
    "Trap": null,
    "Key": null,
    "Soul": null,
    "Charge": 0,
    "Blocked": 0
  },
  {
    "Id": "flora_ash_grass_b_01",
    "Translation": [
      39783.508,
      -24540.709,
      750.71204
    ],
    "Rotation": [
      0.0,
      0.0,
      5.5831866
    ],
    "Owner": null,
    "Faction": null,
    "FactionRank": 0,
    "OwnerGlobal": null,
    "Health": 0,
    "Count": 0,
    "Lock": 0,
    "Trap": null,
    "Key": null,
    "Soul": null,
    "Charge": 0,
    "Blocked": 0
  },
  {
    "Id": "terrain_rock_ma_58",
    "Translation": [
      35334.008,
      -17024.62,
      880.4279
    ],
    "Rotation": [
      0.0,
      0.0,
      3.483188
    ],
    "Owner": null,
    "Faction": null,
    "FactionRank": 0,
    "OwnerGlobal": null,
    "Health": 0,
    "Count": 0,
    "Lock": 0,
    "Trap": null,
    "Key": null,
    "Soul": null,
    "Charge": 0,
    "Blocked": 0
  },
  {
    "Id": "terrain_ma_rock13",
    "Translation": [
      35187.566,
      -16831.195,
      676.4085
    ],
    "Rotation": [
      0.3,
      0.59999955,
      0.48318753
    ],
    "Owner": null,
    "Faction": null,
    "FactionRank": 0,
    "OwnerGlobal": null,
    "Health": 0,
    "Count": 0,
    "Lock": 0,
    "Trap": null,
    "Key": null,
    "Soul": null,
    "Charge": 0,
    "Blocked": 0
  },
  {
    "Id": "terrain_rock_ma_51",
    "Translation": [
      34948.754,
      -16751.555,
      553.8359
    ],
    "Rotation": [
      0.0,
      0.0,
      4.966077
    ],
    "Owner": null,
    "Faction": null,
    "FactionRank": 0,
    "OwnerGlobal": null,
    "Health": 0,
    "Count": 0,
    "Lock": 0,
    "Trap": null,
    "Key": null,
    "Soul": null,
    "Charge": 0,
    "Blocked": 0
  },
  {
    "Id": "flora_ash_grass_w_01",
    "Translation": [
      35223.125,
      -16662.58,
      616.51666
    ],
    "Rotation": [
      6.1831856,
      0.3,
      2.683188
    ],
    "Owner": null,
    "Faction": null,
    "FactionRank": 0,
    "OwnerGlobal": null,
    "Health": 0,
    "Count": 0,
    "Lock": 0,
    "Trap": null,
    "Key": null,
    "Soul": null,
    "Charge": 0,
    "Blocked": 0
  },
  {
    "Id": "terrain_rock_ma_07",
    "Translation": [
      35603.367,
      -16899.844,
      614.9528
    ],
    "Rotation": [
      0.0,
      0.0,
      0.48303846
    ],
    "Owner": null,
    "Faction": null,
    "FactionRank": 0,
    "OwnerGlobal": null,
    "Health": 0,
    "Count": 0,
    "Lock": 0,
    "Trap": null,
    "Key": null,
    "Soul": null,
    "Charge": 0,
    "Blocked": 0
  },
  {
    "Id": "terrain_rock_ma_58",
    "Translation": [
      37738.906,
      -18332.2,
      671.3127
    ],
    "Rotation": [
      0.0,
      0.0,
      2.9831874
    ],
    "Owner": null,
    "Faction": null,
    "FactionRank": 0,
    "OwnerGlobal": null,
    "Health": 0,
    "Count": 0,
    "Lock": 0,
    "Trap": null,
    "Key": null,
    "Soul": null,
    "Charge": 0,
    "Blocked": 0
  },
  {
    "Id": "terrain_ma_rock13",
    "Translation": [
      39379.82,
      -19638.91,
      927.2161
    ],
    "Rotation": [
      0.0,
      0.0999996,
      3.5831869
    ],
    "Owner": null,
    "Faction": null,
    "FactionRank": 0,
    "OwnerGlobal": null,
    "Health": 0,
    "Count": 0,
    "Lock": 0,
    "Trap": null,
    "Key": null,
    "Soul": null,
    "Charge": 0,
    "Blocked": 0
  },
  {
    "Id": "terrain_ma_rock13",
    "Translation": [
      39641.953,
      -20007.234,
      1057.1014
    ],
    "Rotation": [
      0.0,
      1.4999998,
      3.5831873
    ],
    "Owner": null,
    "Faction": null,
    "FactionRank": 0,
    "OwnerGlobal": null,
    "Health": 0,
    "Count": 0,
    "Lock": 0,
    "Trap": null,
    "Key": null,
    "Soul": null,
    "Charge": 0,
    "Blocked": 0
  },
  {
    "Id": "terrain_rock_ma_51",
    "Translation": [
      40056.953,
      -19881.684,
      995.9659
    ],
    "Rotation": [
      0.0,
      0.0,
      6.166076
    ],
    "Owner": null,
    "Faction": null,
    "FactionRank": 0,
    "OwnerGlobal": null,
    "Health": 0,
    "Count": 0,
    "Lock": 0,
    "Trap": null,
    "Key": null,
    "Soul": null,
    "Charge": 0,
    "Blocked": 0
  },
  {
    "Id": "flora_ash_grass_w_01",
    "Translation": [
      39115.965,
      -18895.508,
      530.43646
    ],
    "Rotation": [
      0.0,
      0.0,
      3.8831868
    ],
    "Owner": null,
    "Faction": null,
    "FactionRank": 0,
    "OwnerGlobal": null,
    "Health": 0,
    "Count": 0,
    "Lock": 0,
    "Trap": null,
    "Key": null,
    "Soul": null,
    "Charge": 0,
    "Blocked": 0
  },
  {
    "Id": "terrain_rock_ma_07",
    "Translation": [
      37751.41,
      -18111.793,
      712.1336
    ],
    "Rotation": [
      0.0,
      0.0,
      4.483038
    ],
    "Owner": null,
    "Faction": null,
    "FactionRank": 0,
    "OwnerGlobal": null,
    "Health": 0,
    "Count": 0,
    "Lock": 0,
    "Trap": null,
    "Key": null,
    "Soul": null,
    "Charge": 0,
    "Blocked": 0
  },
  {
    "Id": "terrain_rock_ma_53",
    "Translation": [
      39345.582,
      -19744.441,
      976.0716
    ],
    "Rotation": [
      0.0,
      0.0,
      5.1831865
    ],
    "Owner": null,
    "Faction": null,
    "FactionRank": 0,
    "OwnerGlobal": null,
    "Health": 0,
    "Count": 0,
    "Lock": 0,
    "Trap": null,
    "Key": null,
    "Soul": null,
    "Charge": 0,
    "Blocked": 0
  },
  {
    "Id": "terrain_rock_ma_5a",
    "Translation": [
      39158.645,
      -24544.775,
      601.731
    ],
    "Rotation": [
      0.0,
      0.0,
      5.583308
    ],
    "Owner": null,
    "Faction": null,
    "FactionRank": 0,
    "OwnerGlobal": null,
    "Health": 0,
    "Count": 0,
    "Lock": 0,
    "Trap": null,
    "Key": null,
    "Soul": null,
    "Charge": 0,
    "Blocked": 0
  },
  {
    "Id": "terrain_rock_ma_79",
    "Translation": [
      38911.027,
      -19709.045,
      902.9084
    ],
    "Rotation": [
      0.0,
      0.0,
      4.283185
    ],
    "Owner": null,
    "Faction": null,
    "FactionRank": 0,
    "OwnerGlobal": null,
    "Health": 0,
    "Count": 0,
    "Lock": 0,
    "Trap": null,
    "Key": null,
    "Soul": null,
    "Charge": 0,
    "Blocked": 0
  },
  {
    "Id": "terrain_rock_ma_79",
    "Translation": [
      39243.14,
      -19649.916,
      961.35376
    ],
    "Rotation": [
      0.0,
      0.0,
      3.8831863
    ],
    "Owner": null,
    "Faction": null,
    "FactionRank": 0,
    "OwnerGlobal": null,
    "Health": 0,
    "Count": 0,
    "Lock": 0,
    "Trap": null,
    "Key": null,
    "Soul": null,
    "Charge": 0,
    "Blocked": 0
  },
  {
    "Id": "contain_trama_shrub_02",
    "Translation": [
      36928.582,
      -17935.457,
      930.0912
    ],
    "Rotation": [
      0.0,
      0.0,
      3.983187
    ],
    "Owner": null,
    "Faction": null,
    "FactionRank": 0,
    "OwnerGlobal": null,
    "Health": 0,
    "Count": 0,
    "Lock": 0,
    "Trap": null,
    "Key": null,
    "Soul": null,
    "Charge": 0,
    "Blocked": 0
  },
  {
    "Id": "contain_trama_shrub_02",
    "Translation": [
      39587.71,
      -19738.16,
      1129.0956
    ],
    "Rotation": [
      0.0,
      0.0,
      0.20000008
    ],
    "Owner": null,
    "Faction": null,
    "FactionRank": 0,
    "OwnerGlobal": null,
    "Health": 0,
    "Count": 0,
    "Lock": 0,
    "Trap": null,
    "Key": null,
    "Soul": null,
    "Charge": 0,
    "Blocked": 0
  },
  {
    "Id": "flora_ash_log_02",
    "Translation": [
      39752.47,
      -19930.055,
      1077.452
    ],
    "Rotation": [
      0.0,
      6.0824723,
      5.0833087
    ],
    "Owner": null,
    "Faction": null,
    "FactionRank": 0,
    "OwnerGlobal": null,
    "Health": 0,
    "Count": 0,
    "Lock": 0,
    "Trap": null,
    "Key": null,
    "Soul": null,
    "Charge": 0,
    "Blocked": 0
  },
  {
    "Id": "terrain_rock_ma_55",
    "Translation": [
      40518.406,
      -24212.748,
      966.3319
    ],
    "Rotation": [
      0.0,
      0.0,
      0.78318644
    ],
    "Owner": null,
    "Faction": null,
    "FactionRank": 0,
    "OwnerGlobal": null,
    "Health": 0,
    "Count": 0,
    "Lock": 0,
    "Trap": null,
    "Key": null,
    "Soul": null,
    "Charge": 0,
    "Blocked": 0
  },
  {
    "Id": "terrain_rock_ma_54",
    "Translation": [
      38142.188,
      -18373.117,
      1054.954
    ],
    "Rotation": [
      0.0,
      0.0,
      5.4663687
    ],
    "Owner": null,
    "Faction": null,
    "FactionRank": 0,
    "OwnerGlobal": null,
    "Health": 0,
    "Count": 0,
    "Lock": 0,
    "Trap": null,
    "Key": null,
    "Soul": null,
    "Charge": 0,
    "Blocked": 0
  },
  {
    "Id": "terrain_rock_ma_550",
    "Translation": [
      38433.863,
      -17943.975,
      532.9489
    ],
    "Rotation": [
      6.1837015,
      5.883505,
      4.0831127
    ],
    "Owner": null,
    "Faction": null,
    "FactionRank": 0,
    "OwnerGlobal": null,
    "Health": 0,
    "Count": 0,
    "Lock": 0,
    "Trap": null,
    "Key": null,
    "Soul": null,
    "Charge": 0,
    "Blocked": 0
  },
  {
    "Id": "terrain_rock_ma_54",
    "Translation": [
      38100.36,
      -17822.41,
      538.46265
    ],
    "Rotation": [
      0.0,
      4.7683716E-07,
      2.466371
    ],
    "Owner": null,
    "Faction": null,
    "FactionRank": 0,
    "OwnerGlobal": null,
    "Health": 0,
    "Count": 0,
    "Lock": 0,
    "Trap": null,
    "Key": null,
    "Soul": null,
    "Charge": 0,
    "Blocked": 0
  },
  {
    "Id": "flora_ashtree_06",
    "Translation": [
      38428.746,
      -17642.979,
      947.4076
    ],
    "Rotation": [
      0.0,
      0.0,
      0.1
    ],
    "Owner": null,
    "Faction": null,
    "FactionRank": 0,
    "OwnerGlobal": null,
    "Health": 0,
    "Count": 0,
    "Lock": 0,
    "Trap": null,
    "Key": null,
    "Soul": null,
    "Charge": 0,
    "Blocked": 0
  },
  {
    "Id": "terrain_rock_ma_58",
    "Translation": [
      38102.258,
      -17632.084,
      333.34344
    ],
    "Rotation": [
      0.0,
      0.0,
      3.7824483
    ],
    "Owner": null,
    "Faction": null,
    "FactionRank": 0,
    "OwnerGlobal": null,
    "Health": 0,
    "Count": 0,
    "Lock": 0,
    "Trap": null,
    "Key": null,
    "Soul": null,
    "Charge": 0,
    "Blocked": 0
  },
  {
    "Id": "flora_ashtree_03",
    "Translation": [
      38542.883,
      -17637.268,
      509.18307
    ],
    "Rotation": [
      0.0,
      0.0,
      0.1
    ],
    "Owner": null,
    "Faction": null,
    "FactionRank": 0,
    "OwnerGlobal": null,
    "Health": 0,
    "Count": 0,
    "Lock": 0,
    "Trap": null,
    "Key": null,
    "Soul": null,
    "Charge": 0,
    "Blocked": 0
  },
  {
    "Id": "terrain_rock_ma_54",
    "Translation": [
      39810.88,
      -19067.42,
      499.878
    ],
    "Rotation": [
      0.0,
      4.7683716E-07,
      1.3663723
    ],
    "Owner": null,
    "Faction": null,
    "FactionRank": 0,
    "OwnerGlobal": null,
    "Health": 0,
    "Count": 0,
    "Lock": 0,
    "Trap": null,
    "Key": null,
    "Soul": null,
    "Charge": 0,
    "Blocked": 0
  },
  {
    "Id": "terrain_rock_ma_55",
    "Translation": [
      38312.71,
      -18133.756,
      488.2455
    ],
    "Rotation": [
      0.0,
      0.0,
      2.9831855
    ],
    "Owner": null,
    "Faction": null,
    "FactionRank": 0,
    "OwnerGlobal": null,
    "Health": 0,
    "Count": 0,
    "Lock": 0,
    "Trap": null,
    "Key": null,
    "Soul": null,
    "Charge": 0,
    "Blocked": 0
  },
  {
    "Id": "Act_Terrain_lava_ventlg",
    "Translation": [
      38681.637,
      -18047.443,
      557.3528
    ],
    "Rotation": [
      0.0,
      0.0,
      5.666371
    ],
    "Owner": null,
    "Faction": null,
    "FactionRank": 0,
    "OwnerGlobal": null,
    "Health": 0,
    "Count": 0,
    "Lock": 0,
    "Trap": null,
    "Key": null,
    "Soul": null,
    "Charge": 0,
    "Blocked": 0
  },
  {
    "Id": "Act_Terrain_lava_ventlg",
    "Translation": [
      38700.688,
      -17894.398,
      333.1247
    ],
    "Rotation": [
      0.0,
      0.0,
      5.2662487
    ],
    "Owner": null,
    "Faction": null,
    "FactionRank": 0,
    "OwnerGlobal": null,
    "Health": 0,
    "Count": 0,
    "Lock": 0,
    "Trap": null,
    "Key": null,
    "Soul": null,
    "Charge": 0,
    "Blocked": 0
  },
  {
    "Id": "ex_wild_all_lev+0",
    "Translation": [
      38638.17,
      -16672.023,
      215.77959
    ],
    "Rotation": [
      0.0,
      0.0,
      0.0
    ],
    "Owner": null,
    "Faction": null,
    "FactionRank": 0,
    "OwnerGlobal": null,
    "Health": 0,
    "Count": 0,
    "Lock": 0,
    "Trap": null,
    "Key": null,
    "Soul": null,
    "Charge": 0,
    "Blocked": 0
  }
]